storm_agent/__init__.py
storm_agent/cli.py
storm_agent/py.typed
storm_agent/agents/__init__.py
storm_agent/agents/agent.py
storm_agent/agents/base.py
storm_agent/agents/deep_research.py
storm_agent/agents/multi_agent_system.py
storm_agent/agents/web_search.py
storm_agent/tools/__init__.py
storm_agent/tools/approval.py
storm_agent/tools/base.py
storm_agent/tools/google_drive.py
storm_agent/tools/handoff.py
storm_agent/tools/mcp_tool.py
storm_agent/tools/web_search.py
storm_agent/utils/__init__.py
storm_agent/utils/approval.py
storm_agent/utils/connections.py
storm_agent/utils/message_history.py
storm_agent-1.1.0.dist-info/licenses/LICENSE
storm_agent-1.1.0.dist-info/METADATA
storm_agent-1.1.0.dist-info/WHEEL
storm_agent-1.1.0.dist-info/entry_points.txt
storm_agent-1.1.0.dist-info/top_level.txt
storm_agent-1.1.0.dist-info/RECORD
