Metadata-Version: 2.4
Name: storm-agent
Version: 1.1.0
Summary: A powerful framework for building AI agents with Claude
Home-page: https://github.com/storm-agent/storm-agent
Author: Storm Agent Team
Author-email: Storm Agent Team <contact@storm-agent.dev>
Maintainer-email: Storm Agent Team <contact@storm-agent.dev>
License: MIT
Project-URL: Homepage, https://github.com/storm-agent/storm-agent
Project-URL: Documentation, https://storm-agent.readthedocs.io
Project-URL: Repository, https://github.com/storm-agent/storm-agent
Project-URL: Issues, https://github.com/storm-agent/storm-agent/issues
Project-URL: Changelog, https://github.com/storm-agent/storm-agent/blob/main/CHANGELOG.md
Keywords: ai,agents,claude,anthropic,mcp,research,web-search,automation,artificial-intelligence
Classifier: Development Status :: 5 - Production/Stable
Classifier: Intended Audience :: Developers
Classifier: Intended Audience :: Science/Research
Classifier: License :: OSI Approved :: MIT License
Classifier: Operating System :: OS Independent
Classifier: Programming Language :: Python :: 3
Classifier: Programming Language :: Python :: 3.9
Classifier: Programming Language :: Python :: 3.10
Classifier: Programming Language :: Python :: 3.11
Classifier: Programming Language :: Python :: 3.12
Classifier: Topic :: Software Development :: Libraries :: Python Modules
Classifier: Topic :: Scientific/Engineering :: Artificial Intelligence
Classifier: Topic :: Internet :: WWW/HTTP :: Indexing/Search
Classifier: Topic :: Office/Business :: Office Suites
Classifier: Topic :: Text Processing :: General
Requires-Python: >=3.9
License-File: LICENSE
Requires-Dist: anthropic>=0.35.0
Requires-Dist: python-dotenv>=1.0.0
Requires-Dist: requests>=2.31.0
Requires-Dist: beautifulsoup4>=4.12.0
Requires-Dist: firecrawl-py>=0.0.16
Requires-Dist: google-auth>=2.23.0
Requires-Dist: google-auth-oauthlib>=1.1.0
Requires-Dist: google-auth-httplib2>=0.1.1
Requires-Dist: google-api-python-client>=2.100.0
Requires-Dist: tiktoken>=0.5.0
Provides-Extra: mcp
Requires-Dist: mcp>=1.0.0; extra == "mcp"
Provides-Extra: dev
Requires-Dist: pytest>=7.4.0; extra == "dev"
Requires-Dist: pytest-asyncio>=0.21.0; extra == "dev"
Requires-Dist: pytest-cov>=4.1.0; extra == "dev"
Requires-Dist: black>=23.0.0; extra == "dev"
Requires-Dist: flake8>=6.0.0; extra == "dev"
Requires-Dist: mypy>=1.5.0; extra == "dev"
Requires-Dist: pre-commit>=3.4.0; extra == "dev"
Requires-Dist: twine>=4.0.0; extra == "dev"
Requires-Dist: build>=0.10.0; extra == "dev"
Provides-Extra: docs
Requires-Dist: sphinx>=7.0.0; extra == "docs"
Requires-Dist: sphinx-rtd-theme>=1.3.0; extra == "docs"
Requires-Dist: myst-parser>=2.0.0; extra == "docs"
Provides-Extra: test
Requires-Dist: pytest>=7.4.0; extra == "test"
Requires-Dist: pytest-asyncio>=0.21.0; extra == "test"
Requires-Dist: pytest-cov>=4.1.0; extra == "test"
Provides-Extra: full
Requires-Dist: mcp>=1.0.0; extra == "full"
Dynamic: author
Dynamic: home-page
Dynamic: license-file
Dynamic: requires-python
